confusion_matrix_uncertainty/__init__.py
confusion_matrix_uncertainty/__main__.py
confusion_matrix_uncertainty/main.py
confusion_matrix_uncertainty-0.1.0.dist-info/entry_points.txt
confusion_matrix_uncertainty-0.1.0.dist-info/LICENSE
confusion_matrix_uncertainty-0.1.0.dist-info/WHEEL
confusion_matrix_uncertainty-0.1.0.dist-info/METADATA
confusion_matrix_uncertainty-0.1.0.dist-info/RECORD
