Metadata-Version: 2.1
Name: confusion-matrix-uncertainty
Version: 0.1.0
Summary: 
Author: Christian Michelsen
Author-email: christianmichelsen@gmail.com
Requires-Python: >=3.8,<4.0
Classifier: Programming Language :: Python :: 3
Classifier: Programming Language :: Python :: 3.8
Classifier: Programming Language :: Python :: 3.9
Requires-Dist: arviz (>=0.11.2,<0.12.0)
Requires-Dist: pandas (>=1.2.4,<2.0.0)
Requires-Dist: sympy (>=1.8,<2.0)
Requires-Dist: typer[all] (>=0.3.2,<0.4.0)
